openapi2mcp/__init__.py
openapi2mcp/__main__.py
openapi2mcp/auth.py
openapi2mcp/cli.py
openapi2mcp/openapi_parser.py
openapi2mcp/server.py
openapi2mcp/tool_executor.py
openapi2mcp-0.1.1.dist-info/licenses/LICENSE
openapi2mcp-0.1.1.dist-info/METADATA
openapi2mcp-0.1.1.dist-info/WHEEL
openapi2mcp-0.1.1.dist-info/entry_points.txt
openapi2mcp-0.1.1.dist-info/top_level.txt
openapi2mcp-0.1.1.dist-info/RECORD
