Metadata-Version: 2.4
Name: openapi2mcp
Version: 0.1.1
Summary: A tool to convert OpenAPI specs to MCP server with tools
Author: OpenAPI2MCP Contributors
Requires-Python: >=3.8
License-File: LICENSE
Requires-Dist: fastapi>=0.103.0
Requires-Dist: uvicorn>=0.23.2
Requires-Dist: pyyaml>=6.0
Requires-Dist: pydantic>=2.3.0
Requires-Dist: openapi3-parser>=1.1.0
Requires-Dist: requests>=2.31.0
Requires-Dist: python-dotenv>=1.0.0
Requires-Dist: sse-starlette>=1.6.5
Requires-Dist: aiohttp>=3.11.18
Requires-Dist: prance>=25.4.8.0
Requires-Dist: fastmcp>=2.4.0
Provides-Extra: dev
Requires-Dist: black>=23.7.0; extra == "dev"
Requires-Dist: isort>=5.12.0; extra == "dev"
Requires-Dist: pytest>=7.4.0; extra == "dev"
Dynamic: license-file
